pytaa/__init__.py
pytaa/backtest/__init__.py
pytaa/backtest/performance.py
pytaa/backtest/positions.py
pytaa/backtest/returns.py
pytaa/strategy/__init__.py
pytaa/strategy/signals.py
pytaa/strategy/static.py
pytaa/strategy/strategies.py
pytaa/tools/__init__.py
pytaa/tools/data.py
pytaa/tools/logger.py
pytaa/tools/risk.py
pytaa-0.5.1.dist-info/LICENSE.txt
pytaa-0.5.1.dist-info/METADATA
pytaa-0.5.1.dist-info/WHEEL
pytaa-0.5.1.dist-info/top_level.txt
pytaa-0.5.1.dist-info/RECORD
